aiortc/__init__.py
aiortc/clock.py
aiortc/events.py
aiortc/exceptions.py
aiortc/jitterbuffer.py
aiortc/mediastreams.py
aiortc/rate.py
aiortc/rtcconfiguration.py
aiortc/rtcdatachannel.py
aiortc/rtcdtlstransport.py
aiortc/rtcicetransport.py
aiortc/rtcpeerconnection.py
aiortc/rtcrtpparameters.py
aiortc/rtcrtpreceiver.py
aiortc/rtcrtpsender.py
aiortc/rtcrtptransceiver.py
aiortc/rtcsctptransport.py
aiortc/rtcsessiondescription.py
aiortc/rtp.py
aiortc/sdp.py
aiortc/stats.py
aiortc/utils.py
aiortc/codecs/__init__.py
aiortc/codecs/_opus.pyi
aiortc/codecs/_opus.pypy310-pp73-win_amd64.pyd
aiortc/codecs/_vpx.pyi
aiortc/codecs/_vpx.pypy310-pp73-win_amd64.pyd
aiortc/codecs/base.py
aiortc/codecs/g711.py
aiortc/codecs/h264.py
aiortc/codecs/opus.py
aiortc/codecs/vpx.py
aiortc/contrib/__init__.py
aiortc/contrib/media.py
aiortc/contrib/signaling.py
aiortc2-1.8.0.post0.dist-info/LICENSE
aiortc2-1.8.0.post0.dist-info/METADATA
aiortc2-1.8.0.post0.dist-info/WHEEL
aiortc2-1.8.0.post0.dist-info/top_level.txt
aiortc2-1.8.0.post0.dist-info/RECORD
